hi_dohyun/__init__.py
hi_dohyun/hello.py
hi_dohyun-0.8.0.dist-info/METADATA
hi_dohyun-0.8.0.dist-info/WHEEL
hi_dohyun-0.8.0.dist-info/entry_points.txt
hi_dohyun-0.8.0.dist-info/top_level.txt
hi_dohyun-0.8.0.dist-info/RECORD
